code/ex2/vlog/mme_control.v
module mme_control #(
    parameter integer N = 32
) (
    input wire clk,
    input wire rst,
    input wire start,
    input wire ready_MMM,
    input wire [N-1:0] c_MMM,
    input wire [N-1:0] e_log,
    output reg ready_out,
    output reg start_MMM,
    output reg [N-1:0] a_MMM,
    output reg [N-1:0] b_MMM
);

    parameter IDLE = 2'b00;
    parameter SUBSTEP_0 = 2'b01;
    parameter SUBSTEP_1 = 2'b10;

    reg [N-1:0] cnt;
    reg [1:0] state;
    reg [N-1:0] m_reg;
    reg [N-1:0] r_reg;
    reg [N-1:0] e_reg;

    always @(posedge clk or posedge rst) begin
        if (rst) begin
            cnt <= 0;
            state <= IDLE;
            ready_out <= 0;
            start_MMM <= 0;
            m_reg <= 0; // If m_reg needs to be initialized to a specific value, set it here.
            r_reg <= 1;
            e_reg <= 0;
            a_MMM <= 0;
            b_MMM <= 0;
        end else begin
            case (state)
                IDLE: begin
                    if (start) begin
                        e_reg <= e_log;
                        cnt <= 0;
                        ready_out <= 0;
                        start_MMM <= 0;
                        m_reg <= c_MMM; // Initializing m_reg with input value
                        state <= SUBSTEP_0;
                    end
                end

                SUBSTEP_0: begin
                    if (cnt < N) begin
                        if (cnt == 0) begin
                            a_MMM <= r_reg;
                            b_MMM <= m_reg;
                        end else begin
                            a_MMM <= r_reg;
                            b_MMM <= e_reg[0] ? m_reg : r_reg;
                        end
                        start_MMM <= 1;
                        state <= SUBSTEP_1;
                    end else begin
                        ready_out <= 1;
                        state <= IDLE;
                    end
                end

                SUBSTEP_1: begin
                    if (ready_MMM) begin
                        start_MMM <= 0;
                        if (e_reg[0]) begin
                            r_reg <= c_MMM;
                        end
                        e_reg <= e_reg >> 1;
                        cnt <= cnt + 1;
                        state <= SUBSTEP_0;
                    end
                end

                default: state <= IDLE;
            endcase
        end
    end

endmodule

code/ex2/vlog/mme_control_tb.v
`timescale 1ns/1ns

module mme_control_tb;

    // Local parameters
    localparam integer N = 32;
    localparam integer CLK_PERIOD = 10;

    // DUT Inputs
    reg clk = 0;
    reg rst = 0;
    reg start = 0;
    reg ready_MMM = 0;
    reg [N-1:0] c_MMM = 0;
    reg [N-1:0] e_log = 0;

    // DUT Outputs
    wire ready_out;
    wire start_MMM;
    wire [N-1:0] a_MMM;
    wire [N-1:0] b_MMM;

    // Generate clk
    always #(CLK_PERIOD / 2) clk = ~clk;

    // DUT
    mme_control #(
        .N(N)
    ) u_dut (
        .clk(clk),
        .rst(rst),
        .start(start),
        .ready_MMM(ready_MMM),
        .c_MMM(c_MMM),
        .e_log(e_log),
        .ready_out(ready_out),
        .start_MMM(start_MMM),
        .a_MMM(a_MMM),
        .b_MMM(b_MMM)
    );

    // Test sequence
    initial begin
        // dumpfile for GTKWave
        $dumpfile("mme_control_tb.vcd");
        $dumpvars(0, mme_control_tb);


        rst <= 1;
        #(2 * CLK_PERIOD);
        rst <= 0;

        
        #(5 * CLK_PERIOD);

        // Test 1
        e_log <= 32'h12345678;
        start <= 1;
        #(CLK_PERIOD);
        start <= 0;
        
        // Provide ready_MMM signal and c_MMM value after start_MMM is set
        #(10 * CLK_PERIOD);
        ready_MMM <= 1;
        c_MMM <= 32'h87654321;
        #(CLK_PERIOD);
        ready_MMM <= 0;
        #(10 * CLK_PERIOD);

        // Test 2
        e_log <= 32'h9abcdef0;
        start <= 1;
        #(CLK_PERIOD);
        start <= 0;

        #(10 * CLK_PERIOD);
        ready_MMM <= 1;
        c_MMM <= 32'h0fedcba9;
        #(CLK_PERIOD);
        ready_MMM <= 0;
        #(10 * CLK_PERIOD);

        // End simulation
        #(10 * CLK_PERIOD);
        $finish;
    end

    // Monitor signals
    initial begin
        $monitor("At time %t: start=%b, ready_out=%b, start_MMM=%b, a_MMM=0x%H, b_MMM=0x%H, e_log=0x%H, r_reg=0x%H, state=%b",
                 $time, start, ready_out, start_MMM, a_MMM, b_MMM, e_log, u_dut.r_reg, u_dut.state);
    end

endmodule

code/ex2/vlog/mme_control_tb.vcd
$date
	Fri Jun  7 13:42:21 2024
$end
$version
	Icarus Verilog
$end
$timescale
	1ns
$end
$scope module mme_control_tb $end
$var wire 1 ! start_MMM $end
$var wire 1 " ready_out $end
$var wire 32 # b_MMM [31:0] $end
$var wire 32 $ a_MMM [31:0] $end
$var parameter 32 % CLK_PERIOD $end
$var parameter 32 & N $end
$var reg 32 ' c_MMM [31:0] $end
$var reg 1 ( clk $end
$var reg 32 ) e_log [31:0] $end
$var reg 1 * ready_MMM $end
$var reg 1 + rst $end
$var reg 1 , start $end
$scope module u_dut $end
$var wire 32 - c_MMM [31:0] $end
$var wire 1 ( clk $end
$var wire 32 . e_log [31:0] $end
$var wire 1 * ready_MMM $end
$var wire 1 + rst $end
$var wire 1 , start $end
$var parameter 2 / IDLE $end
$var parameter 32 0 N $end
$var parameter 2 1 SUBSTEP_0 $end
$var parameter 2 2 SUBSTEP_1 $end
$var reg 32 3 a_MMM [31:0] $end
$var reg 32 4 b_MMM [31:0] $end
$var reg 32 5 cnt [31:0] $end
$var reg 32 6 e_reg [31:0] $end
$var reg 32 7 m_reg [31:0] $end
$var reg 32 8 r_reg [31:0] $end
$var reg 1 " ready_out $end
$var reg 1 ! start_MMM $end
$var reg 2 9 state [1:0] $end
$upscope $end
$upscope $end
$enddefinitions $end
$comment Show the parameter values. $end
$dumpall
b10 2
b1 1
b100000 0
b0 /
b100000 &
b1010 %
$end
#0
$dumpvars
b0 9
b1 8
b0 7
b0 6
b0 5
b0 4
b0 3
b0 .
b0 -
0,
1+
0*
b0 )
0(
b0 '
b0 $
b0 #
0"
0!
$end
#5
1(
#10
0(
#15
1(
#20
0+
0(
#25
1(
#30
0(
#35
1(
#40
0(
#45
1(
#50
0(
#55
1(
#60
0(
#65
1(
#70
1,
b10010001101000101011001111000 )
b10010001101000101011001111000 .
0(
#75
b1 9
b10010001101000101011001111000 6
1(
#80
0,
0(
#85
b10 9
1!
b1 $
b1 3
1(
#90
0(
#95
1(
#100
0(
#105
1(
#110
0(
#115
1(
#120
0(
#125
1(
#130
0(
#135
1(
#140
0(
#145
1(
#150
0(
#155
1(
#160
0(
#165
1(
#170
0(
#175
1(
#180
b10000111011001010100001100100001 '
b10000111011001010100001100100001 -
1*
0(
#185
b1 9
b1 5
b1001000110100010101100111100 6
0!
1(
#190
0*
0(
#195
b10 9
1!
b1 #
b1 4
1(
#200
0(
#205
1(
#210
0(
#215
1(
#220
0(
#225
1(
#230
0(
#235
1(
#240
0(
#245
1(
#250
0(
#255
1(
#260
0(
#265
1(
#270
0(
#275
1(
#280
0(
#285
1(
#290
1,
b10011010101111001101111011110000 )
b10011010101111001101111011110000 .
0(
#295
1(
#300
0,
0(
#305
1(
#310
0(
#315
1(
#320
0(
#325
1(
#330
0(
#335
1(
#340
0(
#345
1(
#350
0(
#355
1(
#360
0(
#365
1(
#370
0(
#375
1(
#380
0(
#385
1(
#390
0(
#395
1(
#400
b1111111011011100101110101001 '
b1111111011011100101110101001 -
1*
0(
#405
b1 9
b10 5
b100100011010001010110011110 6
0!
1(
#410
0*
0(
#415
b10 9
1!
1(
